LICENSE.txt
MANIFEST.in
README.md
setup.json
setup.py
aiida_symmetry_representation/__init__.py
aiida_symmetry_representation.egg-info/PKG-INFO
aiida_symmetry_representation.egg-info/SOURCES.txt
aiida_symmetry_representation.egg-info/dependency_links.txt
aiida_symmetry_representation.egg-info/entry_points.txt
aiida_symmetry_representation.egg-info/requires.txt
aiida_symmetry_representation.egg-info/top_level.txt
aiida_symmetry_representation/calculations/__init__.py
aiida_symmetry_representation/calculations/filter_symmetries.py
aiida_symmetry_representation/parsers/__init__.py
aiida_symmetry_representation/parsers/symmetries.py